README.md
setup.py
gemini_python_api/__init__.py
gemini_python_api.egg-info/PKG-INFO
gemini_python_api.egg-info/SOURCES.txt
gemini_python_api.egg-info/dependency_links.txt
gemini_python_api.egg-info/top_level.txt
gemini_python_api/account/__init__.py
gemini_python_api/account/account_detail.py
gemini_python_api/coininfo/__init__.py
gemini_python_api/coininfo/public_info.py
gemini_python_api/orders/__init__.py
gemini_python_api/orders/cancel_order.py
gemini_python_api/orders/new_order.py
gemini_python_api/orders/order_status.py